MANIFEST.in
README.txt
setup.py
docs/HISTORY.txt
docs/LICENSE.txt
src/silva/__init__.py
src/silva.ui.egg-info/PKG-INFO
src/silva.ui.egg-info/SOURCES.txt
src/silva.ui.egg-info/dependency_links.txt
src/silva.ui.egg-info/entry_points.txt
src/silva.ui.egg-info/namespace_packages.txt
src/silva.ui.egg-info/requires.txt
src/silva.ui.egg-info/top_level.txt
src/silva.ui.egg-info/zip-safe
src/silva/ui/__init__.py
src/silva/ui/batching.py
src/silva/ui/configure.zcml
src/silva/ui/icon.py
src/silva/ui/interfaces.py
src/silva/ui/layout.py
src/silva/ui/menu.py
src/silva/ui/service.png
src/silva/ui/service.py
src/silva/ui/smi.py
src/silva/ui/batching_templates/restbatchview.cpt
src/silva/ui/batching_templates/restdatebatchview.cpt
src/silva/ui/layout_templates/defaultlayout.cpt
src/silva/ui/martiansupport/__init__.py
src/silva/ui/martiansupport/menu.py
src/silva/ui/martiansupport/page.py
src/silva/ui/rest/__init__.py
src/silva/ui/rest/base.py
src/silva/ui/rest/errors.py
src/silva/ui/rest/exceptions.py
src/silva/ui/rest/helper.py
src/silva/ui/rest/invalidation.py
src/silva/ui/rest/utils.py
src/silva/ui/rest/container/__init__.py
src/silva/ui/rest/container/configuration.py
src/silva/ui/rest/container/generator.py
src/silva/ui/rest/container/listing.py
src/silva/ui/rest/container/notifier.py
src/silva/ui/rest/container/serializer.py
src/silva/ui/rest/container/templates/listing.cpt
src/silva/ui/rest/container/templates/listingtoolbar.cpt
src/silva/ui/smi_templates/smitemplate.cpt
src/silva/ui/static/css/actions.css
src/silva/ui/static/css/actions.min.css
src/silva/ui/static/css/forms.css
src/silva/ui/static/css/forms.min.css
src/silva/ui/static/css/formwidgets.css
src/silva/ui/static/css/formwidgets.min.css
src/silva/ui/static/css/jstree.css
src/silva/ui/static/css/jstree.min.css
src/silva/ui/static/css/listing.css
src/silva/ui/static/css/listing.min.css
src/silva/ui/static/css/navigation.css
src/silva/ui/static/css/navigation.min.css
src/silva/ui/static/css/smi.css
src/silva/ui/static/css/smi.min.css
src/silva/ui/static/css/style.css
src/silva/ui/static/css/style.min.css
src/silva/ui/static/img/apple-touch-icon.png
src/silva/ui/static/img/arrow-down.png
src/silva/ui/static/img/gradient-tab-selected.png
src/silva/ui/static/img/gradient-tab.png
