Metadata-Version: 1.1
Name: silva.ui
Version: 3.0.3
Summary: Components for the user-interface to manage Silva CMS
Home-page: https://github.com/silvacms/silva.ui
Author: Infrae
Author-email: info@infrae.com
License: BSD
Keywords: silva management interface SMI
Platform: UNKNOWN
Classifier: Programming Language :: Python
